{
 "ticker": "ADBE",
 "name": "어도비",
 "price": 225.11,
 "dataAsOf": "2026-07-24",
 "score": 80,
 "label": "매우 강세",
 "ratioText": "상승 베팅이 하락의 1.8배 — 강세 우위",
 "buckets": [
  {
   "strike": 186.5,
   "callOi": 1314,
   "putOi": 9433
  },
  {
   "strike": 199.4,
   "callOi": 5253,
   "putOi": 17619
  },
  {
   "strike": 212.2,
   "callOi": 6375,
   "putOi": 12339
  },
  {
   "strike": 225.1,
   "callOi": 17513,
   "putOi": 14575
  },
  {
   "strike": 238.0,
   "callOi": 14575,
   "putOi": 5030
  },
  {
   "strike": 250.8,
   "callOi": 14737,
   "putOi": 4907
  },
  {
   "strike": 263.7,
   "callOi": 10131,
   "putOi": 2274
  }
 ],
 "maxPain": 225.0,
 "trend": [
  {
   "date": "2026-07-03",
   "score": 89,
   "price": 219.72
  },
  {
   "date": "2026-07-06",
   "score": 47,
   "price": 218.07
  },
  {
   "date": "2026-07-07",
   "score": 90,
   "price": 221.54
  },
  {
   "date": "2026-07-08",
   "score": 74,
   "price": 220.94
  },
  {
   "date": "2026-07-09",
   "score": 61,
   "price": 222.65
  },
  {
   "date": "2026-07-10",
   "score": 89,
   "price": 223.64
  },
  {
   "date": "2026-07-13",
   "score": 74,
   "price": 230.61
  },
  {
   "date": "2026-07-14",
   "score": 74,
   "price": 220.78
  },
  {
   "date": "2026-07-15",
   "score": 70,
   "price": 224.56
  },
  {
   "date": "2026-07-16",
   "score": 83,
   "price": 235.31
  },
  {
   "date": "2026-07-17",
   "score": 90,
   "price": 237.25
  },
  {
   "date": "2026-07-20",
   "score": 71,
   "price": 234.74
  },
  {
   "date": "2026-07-21",
   "score": 60,
   "price": 227.16
  },
  {
   "date": "2026-07-22",
   "score": 58,
   "price": 218.36
  },
  {
   "date": "2026-07-23",
   "score": 46,
   "price": 212.17
  },
  {
   "date": "2026-07-24",
   "score": 80,
   "price": 225.11
  }
 ]
}