{
 "ticker": "DLTR",
 "name": "달러트리",
 "price": 121.46,
 "dataAsOf": "2026-07-06",
 "score": 10,
 "label": "매우 약세",
 "ratioText": "하락 베팅이 상승의 2.3배 — 약세 우위",
 "buckets": [
  {
   "strike": 100.6,
   "callOi": 559,
   "putOi": 1853
  },
  {
   "strike": 107.6,
   "callOi": 1433,
   "putOi": 2880
  },
  {
   "strike": 114.5,
   "callOi": 1394,
   "putOi": 1176
  },
  {
   "strike": 121.5,
   "callOi": 1844,
   "putOi": 957
  },
  {
   "strike": 128.4,
   "callOi": 4227,
   "putOi": 5065
  },
  {
   "strike": 135.3,
   "callOi": 575,
   "putOi": 60
  },
  {
   "strike": 142.3,
   "callOi": 884,
   "putOi": 0
  }
 ],
 "maxPain": 120.0,
 "trend": [
  {
   "date": "2026-07-03",
   "score": 10,
   "price": 124.05
  },
  {
   "date": "2026-07-06",
   "score": 10,
   "price": 121.46
  }
 ]
}