{
 "ticker": "GS",
 "name": "골드만삭스",
 "price": 1021.0,
 "dataAsOf": "2026-07-03",
 "score": 71,
 "label": "강세",
 "ratioText": "상승 베팅이 하락의 1.4배 — 강세 우위",
 "buckets": [
  {
   "strike": 846.0,
   "callOi": 2728,
   "putOi": 6420
  },
  {
   "strike": 904.3,
   "callOi": 2985,
   "putOi": 9231
  },
  {
   "strike": 962.7,
   "callOi": 3963,
   "putOi": 8354
  },
  {
   "strike": 1021.0,
   "callOi": 5925,
   "putOi": 7006
  },
  {
   "strike": 1079.3,
   "callOi": 10692,
   "putOi": 2233
  },
  {
   "strike": 1137.7,
   "callOi": 5679,
   "putOi": 605
  },
  {
   "strike": 1196.0,
   "callOi": 5413,
   "putOi": 142
  }
 ],
 "trend": [
  {
   "date": "2026-07-03",
   "score": 71
  }
 ]
}