{
 "ticker": "KDP",
 "name": "큐리그닥터페퍼",
 "price": 31.25,
 "dataAsOf": "2026-07-13",
 "score": 90,
 "label": "매우 강세",
 "ratioText": "상승 베팅이 하락의 32.3배 — 강세 우위",
 "buckets": [
  {
   "strike": 25.9,
   "callOi": 1,
   "putOi": 892
  },
  {
   "strike": 27.7,
   "callOi": 19,
   "putOi": 682
  },
  {
   "strike": 29.5,
   "callOi": 775,
   "putOi": 1016
  },
  {
   "strike": 31.2,
   "callOi": 3947,
   "putOi": 1418
  },
  {
   "strike": 33.0,
   "callOi": 4344,
   "putOi": 156
  },
  {
   "strike": 34.8,
   "callOi": 4051,
   "putOi": 4
  },
  {
   "strike": 36.6,
   "callOi": 72,
   "putOi": 0
  }
 ],
 "maxPain": 31.0,
 "trend": [
  {
   "date": "2026-07-03",
   "score": 90,
   "price": 33.3
  },
  {
   "date": "2026-07-06",
   "score": 90,
   "price": 31.75
  },
  {
   "date": "2026-07-07",
   "score": 90,
   "price": 31.49
  },
  {
   "date": "2026-07-08",
   "score": 90,
   "price": 30.97
  },
  {
   "date": "2026-07-09",
   "score": 90,
   "price": 30.72
  },
  {
   "date": "2026-07-10",
   "score": 90,
   "price": 31.67
  },
  {
   "date": "2026-07-13",
   "score": 90,
   "price": 31.25
  }
 ]
}