{
 "ticker": "LCID",
 "name": "루시드",
 "price": 5.51,
 "dataAsOf": "2026-07-13",
 "score": 81,
 "label": "매우 강세",
 "ratioText": "상승 베팅이 하락의 1.9배 — 강세 우위",
 "buckets": [
  {
   "strike": 4.6,
   "callOi": 13889,
   "putOi": 2400
  },
  {
   "strike": 4.9,
   "callOi": 6042,
   "putOi": 22162
  },
  {
   "strike": 5.2,
   "callOi": 0,
   "putOi": 0
  },
  {
   "strike": 5.5,
   "callOi": 4352,
   "putOi": 4212
  },
  {
   "strike": 5.8,
   "callOi": 0,
   "putOi": 0
  },
  {
   "strike": 6.1,
   "callOi": 14580,
   "putOi": 24995
  },
  {
   "strike": 6.5,
   "callOi": 2592,
   "putOi": 805
  }
 ],
 "maxPain": 7.0,
 "trend": [
  {
   "date": "2026-07-03",
   "score": 10,
   "price": 6.08
  },
  {
   "date": "2026-07-06",
   "score": 10,
   "price": 6.66
  },
  {
   "date": "2026-07-07",
   "score": 34,
   "price": 5.99
  },
  {
   "date": "2026-07-08",
   "score": 55,
   "price": 5.82
  },
  {
   "date": "2026-07-09",
   "score": 70,
   "price": 5.83
  },
  {
   "date": "2026-07-10",
   "score": 63,
   "price": 5.55
  },
  {
   "date": "2026-07-13",
   "score": 81,
   "price": 5.51
  }
 ]
}