{
 "ticker": "LRCX",
 "name": "램리서치",
 "price": 353.17,
 "dataAsOf": "2026-07-09",
 "score": 79,
 "label": "강세",
 "ratioText": "상승 베팅이 하락의 1.8배 — 강세 우위",
 "buckets": [
  {
   "strike": 292.6,
   "callOi": 3485,
   "putOi": 24426
  },
  {
   "strike": 312.8,
   "callOi": 8346,
   "putOi": 14459
  },
  {
   "strike": 333.0,
   "callOi": 10610,
   "putOi": 11404
  },
  {
   "strike": 353.2,
   "callOi": 8720,
   "putOi": 17741
  },
  {
   "strike": 373.4,
   "callOi": 12787,
   "putOi": 6128
  },
  {
   "strike": 393.5,
   "callOi": 17275,
   "putOi": 8852
  },
  {
   "strike": 413.7,
   "callOi": 7994,
   "putOi": 1767
  }
 ],
 "maxPain": 350.0,
 "trend": [
  {
   "date": "2026-07-03",
   "score": 55,
   "price": 351.41
  },
  {
   "date": "2026-07-06",
   "score": 10,
   "price": 350.2
  },
  {
   "date": "2026-07-07",
   "score": 51,
   "price": 326.13
  },
  {
   "date": "2026-07-08",
   "score": 87,
   "price": 333.15
  },
  {
   "date": "2026-07-09",
   "score": 79,
   "price": 353.17
  }
 ]
}