{
 "ticker": "LULU",
 "name": "룰루레몬",
 "price": 116.51,
 "dataAsOf": "2026-07-09",
 "score": 58,
 "label": "중립",
 "ratioText": "상승·하락 베팅 비슷 — 관망 분위기",
 "buckets": [
  {
   "strike": 96.5,
   "callOi": 203,
   "putOi": 1627
  },
  {
   "strike": 103.2,
   "callOi": 3029,
   "putOi": 15008
  },
  {
   "strike": 109.9,
   "callOi": 4175,
   "putOi": 8438
  },
  {
   "strike": 116.5,
   "callOi": 5175,
   "putOi": 5251
  },
  {
   "strike": 123.2,
   "callOi": 16921,
   "putOi": 3936
  },
  {
   "strike": 129.8,
   "callOi": 8353,
   "putOi": 1490
  },
  {
   "strike": 136.5,
   "callOi": 3192,
   "putOi": 1364
  }
 ],
 "maxPain": 115.0,
 "trend": [
  {
   "date": "2026-07-03",
   "score": 84,
   "price": 118.43
  },
  {
   "date": "2026-07-06",
   "score": 79,
   "price": 115.64
  },
  {
   "date": "2026-07-07",
   "score": 70,
   "price": 115.07
  },
  {
   "date": "2026-07-08",
   "score": 87,
   "price": 113.62
  },
  {
   "date": "2026-07-09",
   "score": 58,
   "price": 116.51
  }
 ]
}