{
 "ticker": "META",
 "name": "메타",
 "price": 681.31,
 "dataAsOf": "2026-07-15",
 "score": 90,
 "label": "매우 강세",
 "ratioText": "상승 베팅이 하락의 2.8배 — 강세 우위",
 "buckets": [
  {
   "strike": 564.5,
   "callOi": 25729,
   "putOi": 71701
  },
  {
   "strike": 603.4,
   "callOi": 69435,
   "putOi": 69348
  },
  {
   "strike": 642.4,
   "callOi": 107002,
   "putOi": 41837
  },
  {
   "strike": 681.3,
   "callOi": 178138,
   "putOi": 12455
  },
  {
   "strike": 720.2,
   "callOi": 80329,
   "putOi": 2794
  },
  {
   "strike": 759.2,
   "callOi": 74944,
   "putOi": 796
  },
  {
   "strike": 798.1,
   "callOi": 42627,
   "putOi": 732
  }
 ],
 "maxPain": 610.0,
 "trend": [
  {
   "date": "2026-07-03",
   "score": 89,
   "price": 582.9
  },
  {
   "date": "2026-07-06",
   "score": 90,
   "price": 600.29
  },
  {
   "date": "2026-07-07",
   "score": 90,
   "price": 615.58
  },
  {
   "date": "2026-07-08",
   "score": 77,
   "price": 603.12
  },
  {
   "date": "2026-07-09",
   "score": 90,
   "price": 631.48
  },
  {
   "date": "2026-07-10",
   "score": 89,
   "price": 669.21
  },
  {
   "date": "2026-07-13",
   "score": 76,
   "price": 656.73
  },
  {
   "date": "2026-07-14",
   "score": 85,
   "price": 661.04
  },
  {
   "date": "2026-07-15",
   "score": 90,
   "price": 681.31
  }
 ]
}