{
 "ticker": "MRVL",
 "name": "마벨",
 "price": 235.81,
 "dataAsOf": "2026-07-10",
 "score": 61,
 "label": "강세",
 "ratioText": "상승 베팅이 하락의 1.2배 — 강세 우위",
 "buckets": [
  {
   "strike": 195.4,
   "callOi": 15995,
   "putOi": 34455
  },
  {
   "strike": 208.9,
   "callOi": 6453,
   "putOi": 14737
  },
  {
   "strike": 222.3,
   "callOi": 8545,
   "putOi": 19871
  },
  {
   "strike": 235.8,
   "callOi": 24650,
   "putOi": 27246
  },
  {
   "strike": 249.3,
   "callOi": 30815,
   "putOi": 19621
  },
  {
   "strike": 262.8,
   "callOi": 26742,
   "putOi": 8483
  },
  {
   "strike": 276.2,
   "callOi": 39924,
   "putOi": 18188
  }
 ],
 "maxPain": 230.0,
 "trend": [
  {
   "date": "2026-07-03",
   "score": 44,
   "price": 245.29
  },
  {
   "date": "2026-07-06",
   "score": 81,
   "price": 249.27
  },
  {
   "date": "2026-07-07",
   "score": 82,
   "price": 230.7
  },
  {
   "date": "2026-07-08",
   "score": 81,
   "price": 231.71
  },
  {
   "date": "2026-07-09",
   "score": 78,
   "price": 243.27
  },
  {
   "date": "2026-07-10",
   "score": 61,
   "price": 235.81
  }
 ]
}