{
 "ticker": "NEE",
 "name": "넥스트에라에너지",
 "price": 87.1,
 "dataAsOf": "2026-07-09",
 "score": 49,
 "label": "중립",
 "ratioText": "상승·하락 베팅 비슷 — 관망 분위기",
 "buckets": [
  {
   "strike": 72.2,
   "callOi": 23,
   "putOi": 108
  },
  {
   "strike": 77.1,
   "callOi": 105,
   "putOi": 2301
  },
  {
   "strike": 82.1,
   "callOi": 537,
   "putOi": 10178
  },
  {
   "strike": 87.1,
   "callOi": 11784,
   "putOi": 14898
  },
  {
   "strike": 92.1,
   "callOi": 22213,
   "putOi": 2924
  },
  {
   "strike": 97.1,
   "callOi": 6805,
   "putOi": 811
  },
  {
   "strike": 102.0,
   "callOi": 959,
   "putOi": 0
  }
 ],
 "maxPain": 87.5,
 "trend": [
  {
   "date": "2026-07-03",
   "score": 90,
   "price": 88.34
  },
  {
   "date": "2026-07-06",
   "score": 57,
   "price": 87.44
  },
  {
   "date": "2026-07-07",
   "score": 29,
   "price": 88.47
  },
  {
   "date": "2026-07-08",
   "score": 63,
   "price": 87.44
  },
  {
   "date": "2026-07-09",
   "score": 49,
   "price": 87.1
  }
 ]
}