{
 "ticker": "RDDT",
 "name": "레딧",
 "price": 195.34,
 "dataAsOf": "2026-07-10",
 "score": 75,
 "label": "강세",
 "ratioText": "상승 베팅이 하락의 1.6배 — 강세 우위",
 "buckets": [
  {
   "strike": 161.9,
   "callOi": 3413,
   "putOi": 4793
  },
  {
   "strike": 173.0,
   "callOi": 8760,
   "putOi": 5347
  },
  {
   "strike": 184.2,
   "callOi": 7429,
   "putOi": 5793
  },
  {
   "strike": 195.3,
   "callOi": 16270,
   "putOi": 5409
  },
  {
   "strike": 206.5,
   "callOi": 12028,
   "putOi": 2092
  },
  {
   "strike": 217.7,
   "callOi": 12228,
   "putOi": 638
  },
  {
   "strike": 228.8,
   "callOi": 5124,
   "putOi": 153
  }
 ],
 "maxPain": 175.0,
 "trend": [
  {
   "date": "2026-07-03",
   "score": 90,
   "price": 194.67
  },
  {
   "date": "2026-07-06",
   "score": 90,
   "price": 200.86
  },
  {
   "date": "2026-07-07",
   "score": 80,
   "price": 199.44
  },
  {
   "date": "2026-07-08",
   "score": 78,
   "price": 195.31
  },
  {
   "date": "2026-07-09",
   "score": 90,
   "price": 200.31
  },
  {
   "date": "2026-07-10",
   "score": 75,
   "price": 195.34
  }
 ]
}