{
 "ticker": "REGN",
 "name": "리제네론",
 "price": 649.81,
 "dataAsOf": "2026-07-06",
 "score": 68,
 "label": "강세",
 "ratioText": "상승 베팅이 하락의 1.4배 — 강세 우위",
 "buckets": [
  {
   "strike": 538.4,
   "callOi": 5,
   "putOi": 280
  },
  {
   "strike": 575.5,
   "callOi": 339,
   "putOi": 1022
  },
  {
   "strike": 612.7,
   "callOi": 932,
   "putOi": 1366
  },
  {
   "strike": 649.8,
   "callOi": 1229,
   "putOi": 666
  },
  {
   "strike": 686.9,
   "callOi": 889,
   "putOi": 421
  },
  {
   "strike": 724.1,
   "callOi": 257,
   "putOi": 136
  },
  {
   "strike": 761.2,
   "callOi": 179,
   "putOi": 48
  }
 ],
 "maxPain": 635.0,
 "trend": [
  {
   "date": "2026-07-03",
   "score": 49,
   "price": 654.27
  },
  {
   "date": "2026-07-06",
   "score": 68,
   "price": 649.81
  }
 ]
}