{
 "ticker": "SPGI",
 "name": "S&P글로벌",
 "price": 420.0,
 "dataAsOf": "2026-07-23",
 "score": 10,
 "label": "매우 약세",
 "ratioText": "하락 베팅이 상승의 1.7배 — 약세 우위",
 "buckets": [
  {
   "strike": 348.0,
   "callOi": 35,
   "putOi": 217
  },
  {
   "strike": 372.0,
   "callOi": 40,
   "putOi": 1176
  },
  {
   "strike": 396.0,
   "callOi": 47,
   "putOi": 935
  },
  {
   "strike": 420.0,
   "callOi": 189,
   "putOi": 976
  },
  {
   "strike": 444.0,
   "callOi": 982,
   "putOi": 1235
  },
  {
   "strike": 468.0,
   "callOi": 515,
   "putOi": 206
  },
  {
   "strike": 492.0,
   "callOi": 812,
   "putOi": 100
  }
 ],
 "maxPain": 450.0,
 "trend": [
  {
   "date": "2026-07-03",
   "score": 90,
   "price": 439.89
  },
  {
   "date": "2026-07-06",
   "score": 90,
   "price": 447.22
  },
  {
   "date": "2026-07-07",
   "score": 63,
   "price": 443.46
  },
  {
   "date": "2026-07-08",
   "score": 54,
   "price": 430.79
  },
  {
   "date": "2026-07-09",
   "score": 84,
   "price": 432.96
  },
  {
   "date": "2026-07-10",
   "score": 89,
   "price": 430.5
  },
  {
   "date": "2026-07-13",
   "score": 72,
   "price": 437.84
  },
  {
   "date": "2026-07-14",
   "score": 75,
   "price": 438.87
  },
  {
   "date": "2026-07-15",
   "score": 64,
   "price": 444.48
  },
  {
   "date": "2026-07-16",
   "score": 49,
   "price": 457.38
  },
  {
   "date": "2026-07-17",
   "score": 78,
   "price": 450.84
  },
  {
   "date": "2026-07-20",
   "score": 10,
   "price": 448.35
  },
  {
   "date": "2026-07-21",
   "score": 10,
   "price": 431.26
  },
  {
   "date": "2026-07-22",
   "score": 11,
   "price": 429.06
  },
  {
   "date": "2026-07-23",
   "score": 10,
   "price": 420.0
  }
 ]
}