{
 "ticker": "T",
 "name": "AT&T",
 "price": 21.13,
 "dataAsOf": "2026-07-10",
 "score": 88,
 "label": "매우 강세",
 "ratioText": "상승 베팅이 하락의 2.3배 — 강세 우위",
 "buckets": [
  {
   "strike": 17.5,
   "callOi": 191,
   "putOi": 7621
  },
  {
   "strike": 18.7,
   "callOi": 528,
   "putOi": 31339
  },
  {
   "strike": 19.9,
   "callOi": 4420,
   "putOi": 23436
  },
  {
   "strike": 21.1,
   "callOi": 37677,
   "putOi": 21561
  },
  {
   "strike": 22.3,
   "callOi": 31605,
   "putOi": 25444
  },
  {
   "strike": 23.5,
   "callOi": 80692,
   "putOi": 42986
  },
  {
   "strike": 24.8,
   "callOi": 35517,
   "putOi": 9318
  }
 ],
 "maxPain": 22.5,
 "trend": [
  {
   "date": "2026-07-03",
   "score": 90,
   "price": 20.58
  },
  {
   "date": "2026-07-06",
   "score": 37,
   "price": 20.58
  },
  {
   "date": "2026-07-07",
   "score": 90,
   "price": 21.09
  },
  {
   "date": "2026-07-08",
   "score": 90,
   "price": 21.12
  },
  {
   "date": "2026-07-09",
   "score": 90,
   "price": 21.04
  },
  {
   "date": "2026-07-10",
   "score": 88,
   "price": 21.13
  }
 ]
}