{
 "ticker": "TMO",
 "name": "써모피셔",
 "price": 527.05,
 "dataAsOf": "2026-07-10",
 "score": 45,
 "label": "중립",
 "ratioText": "상승·하락 베팅 비슷 — 관망 분위기",
 "buckets": [
  {
   "strike": 436.7,
   "callOi": 61,
   "putOi": 883
  },
  {
   "strike": 466.8,
   "callOi": 645,
   "putOi": 1922
  },
  {
   "strike": 496.9,
   "callOi": 1225,
   "putOi": 493
  },
  {
   "strike": 527.0,
   "callOi": 1618,
   "putOi": 1084
  },
  {
   "strike": 557.2,
   "callOi": 588,
   "putOi": 3
  },
  {
   "strike": 587.3,
   "callOi": 281,
   "putOi": 0
  },
  {
   "strike": 617.4,
   "callOi": 24,
   "putOi": 0
  }
 ],
 "maxPain": 500.0,
 "trend": [
  {
   "date": "2026-07-03",
   "score": 48,
   "price": 523.44
  },
  {
   "date": "2026-07-06",
   "score": 40,
   "price": 517.6
  },
  {
   "date": "2026-07-07",
   "score": 10,
   "price": 516.62
  },
  {
   "date": "2026-07-08",
   "score": 51,
   "price": 510.13
  },
  {
   "date": "2026-07-09",
   "score": 55,
   "price": 524.71
  },
  {
   "date": "2026-07-10",
   "score": 45,
   "price": 527.05
  }
 ]
}