{
 "ticker": "TTWO",
 "name": "테이크투",
 "price": 239.57,
 "dataAsOf": "2026-07-16",
 "score": 47,
 "label": "중립",
 "ratioText": "상승·하락 베팅 비슷 — 관망 분위기",
 "buckets": [
  {
   "strike": 198.5,
   "callOi": 3227,
   "putOi": 15983
  },
  {
   "strike": 212.2,
   "callOi": 276,
   "putOi": 9537
  },
  {
   "strike": 225.9,
   "callOi": 8755,
   "putOi": 4423
  },
  {
   "strike": 239.6,
   "callOi": 10364,
   "putOi": 4191
  },
  {
   "strike": 253.3,
   "callOi": 10176,
   "putOi": 2015
  },
  {
   "strike": 266.9,
   "callOi": 2561,
   "putOi": 126
  },
  {
   "strike": 280.6,
   "callOi": 1914,
   "putOi": 116
  }
 ],
 "maxPain": 230.0,
 "trend": [
  {
   "date": "2026-07-03",
   "score": 11,
   "price": 254.99
  },
  {
   "date": "2026-07-06",
   "score": 10,
   "price": 258.41
  },
  {
   "date": "2026-07-07",
   "score": 10,
   "price": 257.79
  },
  {
   "date": "2026-07-08",
   "score": 10,
   "price": 251.38
  },
  {
   "date": "2026-07-09",
   "score": 31,
   "price": 246.1
  },
  {
   "date": "2026-07-10",
   "score": 21,
   "price": 243.2
  },
  {
   "date": "2026-07-13",
   "score": 10,
   "price": 244.1
  },
  {
   "date": "2026-07-14",
   "score": 33,
   "price": 237.04
  },
  {
   "date": "2026-07-15",
   "score": 90,
   "price": 243.8
  },
  {
   "date": "2026-07-16",
   "score": 47,
   "price": 239.57
  }
 ]
}